xcaptcha/__init__.py
xcaptcha/defaults/__init__.py
xcaptcha/generator/__init__.py
xcaptcha/generator/captcha_generator.py
xcaptcha/types/__init__.py
xcaptcha/types/captcha.py
xcaptcha-1.0.1.dist-info/LICENSE
xcaptcha-1.0.1.dist-info/METADATA
xcaptcha-1.0.1.dist-info/WHEEL
xcaptcha-1.0.1.dist-info/top_level.txt
xcaptcha-1.0.1.dist-info/RECORD
