Metadata-Version: 2.1
Name: xcaptcha
Version: 1.0.1
Summary: UNKNOWN
Home-page: UNKNOWN
Author: Luca Chang
License: UNKNOWN
Platform: UNKNOWN
Requires-Python: >=3.8
License-File: LICENSE
Requires-Dist: opencv-python
Requires-Dist: numpy
